pixano_inference/__init__.py
pixano_inference/__version__.py
pixano_inference/celery.py
pixano_inference/client.py
pixano_inference/main.py
pixano_inference/settings.py
pixano_inference/data/__init__.py
pixano_inference/data/read_vector_databases.py
pixano_inference/models/__init__.py
pixano_inference/models/base.py
pixano_inference/models/sam2.py
pixano_inference/models/transformers.py
pixano_inference/models/vllm.py
pixano_inference/providers/__init__.py
pixano_inference/providers/base.py
pixano_inference/providers/registry.py
pixano_inference/providers/sam2.py
pixano_inference/providers/transformers.py
pixano_inference/providers/utils.py
pixano_inference/providers/vllm.py
pixano_inference/pydantic/__init__.py
pixano_inference/pydantic/base.py
pixano_inference/pydantic/models.py
pixano_inference/pydantic/nd_array.py
pixano_inference/pydantic/data/__init__.py
pixano_inference/pydantic/data/vector_database.py
pixano_inference/pydantic/tasks/__init__.py
pixano_inference/pydantic/tasks/image/__init__.py
pixano_inference/pydantic/tasks/image/mask_generation.py
pixano_inference/pydantic/tasks/image/utils.py
pixano_inference/pydantic/tasks/image/zero_shot_detection.py
pixano_inference/pydantic/tasks/multimodal/__init__.py
pixano_inference/pydantic/tasks/multimodal/conditional_generation.py
pixano_inference/pydantic/tasks/text/__init__.py
pixano_inference/pydantic/tasks/video/__init__.py
pixano_inference/pydantic/tasks/video/mask_generation.py
pixano_inference/routers/__init__.py
pixano_inference/routers/app.py
pixano_inference/routers/providers.py
pixano_inference/routers/utils.py
pixano_inference/routers/tasks/__init__.py
pixano_inference/routers/tasks/image.py
pixano_inference/routers/tasks/multimodal.py
pixano_inference/routers/tasks/nlp.py
pixano_inference/routers/tasks/tasks.py
pixano_inference/routers/tasks/video.py
pixano_inference/tasks/__init__.py
pixano_inference/tasks/image.py
pixano_inference/tasks/multimodal.py
pixano_inference/tasks/nlp.py
pixano_inference-0.5.6.dist-info/METADATA
pixano_inference-0.5.6.dist-info/WHEEL
pixano_inference-0.5.6.dist-info/entry_points.txt
pixano_inference-0.5.6.dist-info/licenses/LICENSE
pixano_inference-0.5.6.dist-info/RECORD
