Metadata-Version: 2.4
Name: pixano-inference
Version: 0.5.6
Summary: Deploy inference models served for Artificial Intelligence solutions including but not limited to Pixano.
Project-URL: Bug Tracker, http://is154588.intra.cea.fr/pixano/pixano-inference/issues
Project-URL: Download, http://is154588.intra.cea.fr/pixano/pixano-inference
Project-URL: Homepage, http://is154588.intra.cea.fr/pixano/pixano-inference
Project-URL: Source Code, http://is154588.intra.cea.fr/pixano/pixano-inference
Author-email: Julien Denize <julien.denize@cea.fr>
License-File: LICENSE
Keywords: computer vision,deep learning,inference,machine learning,natural language processing,nlp,pytorch
Classifier: Development Status :: 4 - Beta
Classifier: Environment :: Console
Classifier: Environment :: GPU
Classifier: Intended Audience :: Developers
Classifier: Intended Audience :: Education
Classifier: Intended Audience :: Information Technology
Classifier: Intended Audience :: Science/Research
Classifier: Natural Language :: English
Classifier: Operating System :: OS Independent
Classifier: Programming Language :: Python :: 3 :: Only
Classifier: Programming Language :: Python :: 3.10
Classifier: Programming Language :: Python :: 3.11
Classifier: Programming Language :: Python :: 3.12
Classifier: Programming Language :: Python :: 3.13
Classifier: Topic :: Scientific/Engineering :: Artificial Intelligence
Classifier: Topic :: Scientific/Engineering :: Image Processing
Classifier: Topic :: Scientific/Engineering :: Information Analysis
Classifier: Topic :: Software Development :: Libraries
Requires-Python: <3.14,>=3.10
Requires-Dist: celery[redis]==5.5.0rc4
Requires-Dist: click>=8.0.0
Requires-Dist: fastapi>=0.100.0
Requires-Dist: httpx
Requires-Dist: numpy<2.0.0
Requires-Dist: pillow>=9.0.0
Requires-Dist: polars<2.0.0
Requires-Dist: pycocotools
Requires-Dist: pydantic-settings
Requires-Dist: pydantic<3.0.0,>=2.0.0
Requires-Dist: python-dotenv~=1.0.1
Requires-Dist: redis[hiredis]~=5.2.1
Requires-Dist: requests
Requires-Dist: uvicorn>=0.31.0
Provides-Extra: data
Requires-Dist: pylance<0.21.0,>=0.18.0; extra == 'data'
Provides-Extra: docs
Requires-Dist: mike<3.0.0,>=2.1.0; extra == 'docs'
Requires-Dist: mkdocs-gen-files>=0.5.0; extra == 'docs'
Requires-Dist: mkdocs-literate-nav>=0.6.0; extra == 'docs'
Requires-Dist: mkdocs-material<10.0.0,>=9.5.0; extra == 'docs'
Requires-Dist: mkdocs-redirects>=1.2.1; extra == 'docs'
Requires-Dist: mkdocs<2.0.0,>=1.6.0; extra == 'docs'
Requires-Dist: mkdocstrings-python>=1.7.0; extra == 'docs'
Provides-Extra: test
Requires-Dist: pytest; extra == 'test'
Requires-Dist: pytest-asyncio; extra == 'test'
Requires-Dist: pytest-cov; extra == 'test'
Requires-Dist: pytest-coverage; extra == 'test'
Requires-Dist: pytest-httpx; extra == 'test'
Requires-Dist: pytest-mock; extra == 'test'
Requires-Dist: responses; extra == 'test'
Provides-Extra: torch
Requires-Dist: torch<3.0.0,>=2.3.0; extra == 'torch'
Provides-Extra: transformers
Requires-Dist: accelerate; extra == 'transformers'
Requires-Dist: bitsandbytes; extra == 'transformers'
Requires-Dist: torch<3.0.0,>=2.3.0; extra == 'transformers'
Requires-Dist: transformers<5.0.0,>=4.0.0; extra == 'transformers'
Provides-Extra: vllm
Requires-Dist: vllm; extra == 'vllm'
